gsae/__init__.py
gsae/models/__init__.py
gsae/models/gae_model.py
gsae/models/gsae_model.py
gsae/models/gvae_model.py
gsae/models/inv_scattering.py
gsae/scattering/__init__.py
gsae/scattering/scattering.py
gsae/utils/__init__.py
gsae/utils/data_utils.py
gsae/utils/eval_metrics.py
gsae/utils/gnn_modules.py
gsae/utils/load_splits.py
GSAE-0.2.dist-info/LICENSE
GSAE-0.2.dist-info/METADATA
GSAE-0.2.dist-info/WHEEL
GSAE-0.2.dist-info/top_level.txt
GSAE-0.2.dist-info/RECORD
