Metadata-Version: 2.1
Name: GSAE
Version: 0.2
Summary: A small example package
Home-page: https://github.com/KrishnaswamyLab/GSAE
Author: Egbert Castro
Author-email: Egbert Castro <egbert.castro@yale.edu>
Project-URL: Homepage, https://github.com/KrishnaswamyLab/GSAE
Project-URL: Bug Tracker, https://github.com/KrishnaswamyLab/GSAE/issues
Classifier: Programming Language :: Python :: 3
Classifier: License :: OSI Approved :: MIT License
Classifier: Operating System :: OS Independent
Classifier: Topic :: Scientific/Engineering
Requires-Python: >=3.7
License-File: LICENSE
Requires-Dist: argparse
Requires-Dist: numpy (>=1.18.4)
Requires-Dist: scikit-learn (>=0.23.1)
Requires-Dist: scipy (>=1.4.1)
Requires-Dist: torch (>=1.5.0)
Requires-Dist: pytorch-lightning (>=1.0.3)
